create_dataset/__init__.py
create_dataset/bulk_create.py
rescue_dec/ResNetAE_pytorch.py
rescue_dec/Resnet18.py
rescue_dec/__init__.py
rescue_dec/dataset.py
rescue_dec-1.0.1.data/scripts/Rescue.py
rescue_dec-1.0.1.dist-info/LICENSE
rescue_dec-1.0.1.dist-info/METADATA
rescue_dec-1.0.1.dist-info/WHEEL
rescue_dec-1.0.1.dist-info/top_level.txt
rescue_dec-1.0.1.dist-info/RECORD
